mbil/__init__.py
mbil/dataset.py
mbil/mbilscore.py
mbil/mbilsearch.py
mbil/output.py
mbil/scores.py
mbil-0.0.2.dist-info/LICENSE.txt
mbil-0.0.2.dist-info/METADATA
mbil-0.0.2.dist-info/WHEEL
mbil-0.0.2.dist-info/top_level.txt
mbil-0.0.2.dist-info/RECORD
