Metadata-Version: 2.1
Name: mbil
Version: 0.0.2
Summary: The python version of Markov Blanket and Interactive risk factor Learner
Author: Xia Jiang, Chuhan Xu
License-File: LICENSE.txt
